hansel/__init__.py
hansel/hansel.py
hanselx-0.0.92.dist-info/LICENSE
hanselx-0.0.92.dist-info/METADATA
hanselx-0.0.92.dist-info/WHEEL
hanselx-0.0.92.dist-info/top_level.txt
hanselx-0.0.92.dist-info/RECORD
