Metadata-Version: 2.1
Name: hanselx
Version: 0.0.92
Summary: A graph-inspired data structure for determining likely chains of sequences from breadcrumbs of evidence
Home-page: https://github.com/samstudio8/hansel
Author: Sam Nicholls
Author-email: sam@samnicholls.net
Maintainer: Sam Nicholls
Maintainer-email: sam@samnicholls.net
License: UNKNOWN
Platform: UNKNOWN
Classifier: Development Status :: 2 - Pre-Alpha
Classifier: Intended Audience :: Science/Research
Classifier: Topic :: Scientific/Engineering
Classifier: Topic :: Scientific/Engineering :: Bio-Informatics
Classifier: License :: OSI Approved :: MIT License
Requires-Dist: numpy
